LICENSE
pinkie/__init__.py
pinkie/blend.py
pinkie/cmyk.py
pinkie/hsla.py
pinkie/palette.py
pinkie/rgba.py
pinkie/utils.py
pyproject.toml
pinkie-0.0.2.dist-info/LICENSE
pinkie-0.0.2.dist-info/METADATA
pinkie-0.0.2.dist-info/WHEEL
pinkie-0.0.2.dist-info/RECORD
