Metadata-Version: 2.1
Name: pinkie
Version: 0.0.2
Summary: All-in-one solution for color management.
Home-page: https://github.com/EeeMoon/pinkie
License: MIT
Author: EeeMoon
Requires-Python: >=3.10,<4.0
Classifier: License :: OSI Approved :: MIT License
Classifier: Programming Language :: Python :: 3
Classifier: Programming Language :: Python :: 3.10
Classifier: Programming Language :: Python :: 3.11
Classifier: Programming Language :: Python :: 3.12
